{
  "id": "targets",
  "description": "The targets are observations that can be used to evaluate and build forecasts.  We provide the code to access different targets as an asset.",
  "stac_version": "1.0.0",
  "license": "CC0-1.0",
  "stac_extensions": [
    "https://stac-extensions.github.io/scientific/v1.0.0/schema.json",
    "https://stac-extensions.github.io/item-assets/v1.0.0/schema.json",
    "https://stac-extensions.github.io/table/v1.2.0/schema.json"
  ],
  "type": "Collection",
  "links": [
    {
      "rel": "parent",
      "type": "application/json",
      "href": "../catalog.json"
    },
    {
      "rel": "root",
      "type": "application/json",
      "href": "../catalog.json"
    },
    {
      "rel": "self",
      "type": "application/json",
      "href": "collection.json"
    },
    {
      "rel": "cite-as",
      "href": "10.1002/fee.2616"
    },
    {
      "rel": "about",
      "href": "https://projects.ecoforecast.org/usgsrc4cast-docs/",
      "type": "text/html",
      "title": "EFI-USGS River Chlorophyll Forecasting Challenge Documentation"
    },
    {
      "rel": "describedby",
      "href": "https://projects.ecoforecast.org/usgsrc4cast-ci/",
      "title": "EFI-USGS River Chlorophyll Forecast Challenge Dashboard",
      "type": "text/html"
    }
  ],
  "title": "Targets",
  "extent": {
    "spatial": {
      "bbox": [
        [
          -122.6692,
          39.6327,
          -74.7781,
          45.5175
        ]
      ]
    },
    "temporal": {
      "interval": [
        [
          "2009-01-22T00:00:00Z",
          "2024-11-30T00:00:00Z"
        ]
      ]
    }
  },
  "table:columns": [
    {
      "name": "project_id",
      "type": "character",
      "description": "unique project identifier"
    },
    {
      "name": "site_id",
      "type": "character",
      "description": "unique site identifier"
    },
    {
      "name": "datetime",
      "type": "Date",
      "description": "datetime of the observed value (ISO 8601)"
    },
    {
      "name": "duration",
      "type": "character",
      "description": "temporal duration of target (hourly = PT1H, daily = P1D, etc.); follows ISO 8601 duration convention"
    },
    {
      "name": "variable",
      "type": "character",
      "description": "observation variable"
    },
    {
      "name": "observation",
      "type": "numeric",
      "description": "observed value for variable"
    }
  ],
  "assets": {
    "thumbnail": {
      "href": "https://raw.githubusercontent.com/eco4cast/neon4cast-ci/main/catalog/thumbnail_plots/neon_stream.jpg",
      "type": "image/JPEG",
      "roles": [
        "thumbnail"
      ],
      "title": "Test Image"
    },
    "2": {
      "href": "https://sdsc.osn.xsede.org/bio230014-bucket01/challenges/targets/project_id=usgsrc4cast/duration=P1D/river-chl-targets.csv.gz",
      "type": "application/x-parquet",
      "title": "aquatics Target Access",
      "roles": [
        "data"
      ],
      "description": "This R code will return results for the relevant targets file.\n\n### R\n\n```{r}\n# Use code below\n\nurl <- \"https://sdsc.osn.xsede.org/bio230014-bucket01/challenges/targets/project_id=usgsrc4cast/duration=P1D/river-chl-targets.csv.gz\"\ntargets <- readr::read_csv(url, show_col_types = FALSE)\n```"
    }
  }
}
